LICENSE
README.md
setup.cfg
setup.py
hak/__init__.py
hak/cell.py
hak/check_if_ok_to_proceed.py
hak/column.py
hak/duration.py
hak/get_datatype.py
hak/is_0.py
hak/is_none.py
hak/node.py
hak/nop.py
hak/pf.py
hak/puvyz.py
hak/pxyf.py
hak/pxyz.py
hak/rate.py
hak/table.py
hak/terminal.py
hak.egg-info/PKG-INFO
hak.egg-info/SOURCES.txt
hak.egg-info/dependency_links.txt
hak.egg-info/top_level.txt
hak/block/is_a.py
hak/block/remove_double_empty_lines.py
hak/blocks/compare.py
hak/blocks/get_max_height.py
hak/blocks/normalise_heights.py
hak/bool/is_a.py
hak/bool/or_none/fake.py
hak/bool/or_none/is_a.py
hak/bool/random/make.py
hak/bools/count_true.py
hak/classes/block.py
hak/data/kana.py
hak/data/macbook_screen_resolutions.py
hak/data/months.py
hak/data/si_prefixes.py
hak/date/choose_random.py
hak/date/is_a.py
hak/date/is_end_of_financial_year.py
hak/date/is_end_of_month.py
hak/date/is_first_second_or_third_day_of_month.py
hak/date/is_first_week_of_quarter.py
hak/date/is_monday.py
hak/date/is_sunday.py
hak/date/is_weekday.py
hak/date/is_weekend.py
hak/date/select_from_last_n_days.py
hak/date/to_dd_mm_yyyy_str.py
hak/date/to_financial_year.py
hak/date/to_month_name.py
hak/date/to_month_start.py
hak/date/to_utc_timestamp.py
hak/date/public_holiday/is_a.py
hak/date/year/easter_sunday/get.py
hak/dates/same_month.py
hak/datetime/is_a.py
hak/datetime/select_from_last_n_days.py
hak/dict/__init__.py
hak/dict/collect_key_levels.py
hak/dict/convert_to_sql_insertable.py
hak/dict/get_all_keys_and_subkeys_as_set.py
hak/dict/get_max_depth.py
hak/dict/get_or_default.py
hak/dict/get_or_zero.py
hak/dict/get_sorted_keys.py
hak/dict/is_a.py
hak/dict/make_from_key_value_lists.py
hak/dict/pick_by_keys.py
hak/dict/remove_zeroes.py
hak/dict/sum.py
hak/dict/to_max_line_width_str.py
hak/dict/to_node_tree.py
hak/dict/to_str.py
hak/dict/char_and_width/to_str.py
hak/dict/custom_order/apply.py
hak/dict/dict_and_int_divisor/floor_divide.py
hak/dict/durations/__init__.py
hak/dict/durations/load.py
hak/dict/durations/save.py
hak/dict/durations/to_tuple_list_sorted_by_duration.py
hak/dict/durations/update_one.py
