Metadata-Version: 2.1
Name: hak
Version: 0.0.205
Summary: Function Test Pair Toolbox
Home-page: https://github.com/JohnForbes/hak
Author: @JohnRForbes
Author-email: john.robert.forbes@gmail.com
License: MIT
Keywords: hak
Platform: UNKNOWN
Classifier: Programming Language :: Python :: 3
Classifier: License :: OSI Approved :: MIT License
Classifier: Operating System :: OS Independent
Requires-Python: >=3.8
